{"log":{"version":"1.2","creator":{"version":"","name":"Pingdom"},"pages":[{"id":"http://kalindimarketing.com/","title":"http://kalindimarketing.com/","pageTimings":{"_navigation_timing":{"secureConnectionStart":0,"redirectStart":0,"domContentLoadedEventStart":1772783937381,"domContentLoadedEventEnd":1772783937381,"redirectEnd":0,"fetchStart":1772783936752,"navigationStart":1772783936411,"domainLookupEnd":1772783936752,"connectEnd":1772783936752,"unloadEventEnd":0,"requestStart":1772783936772,"responseEnd":1772783936981,"unloadEventStart":0,"domLoading":1772783936984,"connectStart":1772783936752,"loadEventStart":1772783937389,"responseStart":1772783936980,"loadEventEnd":1772783937389,"domComplete":1772783937389,"domInteractive":1772783937257,"domainLookupStart":1772783936752},"onLoad":978,"_fullyLoaded":1139,"onContentLoad":970},"startedDateTime":"2026-03-06T07:58:56.412937Z"}],"entries":[{"pageref":"http://kalindimarketing.com/","startedDateTime":"2026-03-06T07:58:56.412937Z","cache":{},"request":{"cookies":[],"url":"http://kalindimarketing.com/","queryString":[],"headers":[{"name":"accept-language","value":"en-US,en;q=0.8"},{"name":"accept-encoding","value":"gzip, deflate"},{"name":"connection","value":"keep-alive"},{"name":"accept","value":"text/html,application/xhtml+xml,application/xml;q=0.9,image/webp,image/apng,*/*;q=0.8"},{"name":"user-agent","value":"Mozilla/5.0 (X11; Linux x86_64) AppleWebKit/537.36 (KHTML, like Gecko) Ubuntu Chromium/61.0.3163.100 Chrome/61.0.3163.100 Safari/537.36 PingdomPageSpeed/1.0 (pingbot/2.0; +http://www.pingdom.com/)"},{"name":"host","value":"kalindimarketing.com"},{"name":"pragma","value":"no-cache"},{"name":"cache-control","value":"no-cache"},{"name":"upgrade-insecure-requests","value":"1"}],"headersSize":515,"bodySize":0,"method":"GET","httpVersion":""},"timings":{"receive":0,"send":0.0470131636,"ssl":0,"connect":1.5439987183,"dns":11.4199966192,"wait":19.8459923267,"blocked":0},"time":32.8570008278,"response":{"status":301,"cookies":[],"statusText":"Moved Permanently","content":{"mimeType":"","_resourceType":"Redirect","size":0},"headers":[{"name":"nel","value":"{\"report_to\":\"cf-nel\",\"success_fraction\":0.0,\"max_age\":604800}"},{"name":"content-length","value":"0"},{"name":"server","value":"cloudflare"},{"name":"server-timing","value":"cfEdge;dur=15,cfOrigin;dur=0"},{"name":"connection","value":"keep-alive"},{"name":"location","value":"https://kalindimarketing.com/"},{"name":"date","value":"Fri, 06 Mar 2026 07:58:56 GMT"},{"name":"cf-ray","value":"9d7fd172ac98e05a-NRT"},{"name":"alt-svc","value":"h3=\":443\"; ma=86400"},{"name":"report-to","value":"{\"group\":\"cf-nel\",\"max_age\":604800,\"endpoints\":[{\"url\":\"https://a.nel.cloudflare.com/report/v4?s=X31J2y1gpVlOngpLY0qaEruwQlbbtmzMeKYd8X%2FbRqZvAfGhDx0O0N31PEOIK6VcStwz3hyg1iNYUBCaVcj9hTSW55JJLy6ZzbZ3gKamqrLsN833\"}]}"}],"headersSize":577,"redirectURL":"https://kalindimarketing.com/","httpVersion":"","bodySize":0}},{"pageref":"http://kalindimarketing.com/","startedDateTime":"2026-03-06T07:58:56.453006Z","cache":{},"request":{"cookies":[],"url":"https://kalindimarketing.com/","queryString":[],"headers":[{"name":"accept-language","value":"en-US,en;q=0.8"},{"name":"accept-encoding","value":"gzip, deflate, br"},{"name":"accept","value":"text/html,application/xhtml+xml,application/xml;q=0.9,image/webp,image/apng,*/*;q=0.8"},{"name":"user-agent","value":"Mozilla/5.0 (X11; Linux x86_64) AppleWebKit/537.36 (KHTML, like Gecko) Ubuntu Chromium/61.0.3163.100 Chrome/61.0.3163.100 Safari/537.36 PingdomPageSpeed/1.0 (pingbot/2.0; +http://www.pingdom.com/)"},{"name":"pragma","value":"no-cache"},{"name":"cache-control","value":"no-cache"},{"name":"upgrade-insecure-requests","value":"1"}],"headersSize":467,"bodySize":0,"method":"GET","httpVersion":""},"timings":{"receive":0,"send":0.1939982176,"ssl":24.7630029917,"connect":25.6810039282,"dns":0,"wait":273.1459885836,"blocked":0},"time":323.783993721,"response":{"status":301,"cookies":[],"statusText":"","content":{"mimeType":"text/html","_resourceType":"Redirect","size":0},"headers":[{"name":"status","value":"301"},{"name":"nel","value":"{\"report_to\":\"cf-nel\",\"success_fraction\":0.0,\"max_age\":604800}"},{"name":"via","value":"1.1 varnish"},{"name":"cf-cache-status","value":"DYNAMIC"},{"name":"x-cache","value":"HIT"},{"name":"x-github-request-id","value":"F89C:1E8E62:3D76A2:3F695D:69AA7C39"},{"name":"accept-ranges","value":"bytes"},{"name":"x-timer","value":"S1772783937.746015,VS0,VE1"},{"name":"vary","value":"Accept-Encoding"},{"name":"server","value":"cloudflare"},{"name":"server-timing","value":"cfCacheStatus;desc=\"DYNAMIC\"\ncfEdge;dur=270,cfOrigin;dur=0"},{"name":"x-fastly-request-id","value":"687b4c9e0102861e1c6147819e15e77c263b0822"},{"name":"x-cache-hits","value":"0"},{"name":"report-to","value":"{\"group\":\"cf-nel\",\"max_age\":604800,\"endpoints\":[{\"url\":\"https://a.nel.cloudflare.com/report/v4?s=oTOBIwauMhrOrSGTx3cpnpj3Z%2B7msjr8TDQNFZolOBcIj6AuHqvgJGWHeLIODhPESJCOA2UF8LcTFatKH0pfkF3UNv0LQdy5o%2F4%2BqbcMVl3NrWgQ\"}]}"},{"name":"x-served-by","value":"cache-nrt-rjtf7700030-NRT"},{"name":"date","value":"Fri, 06 Mar 2026 07:58:56 GMT"},{"name":"cf-ray","value":"9d7fd172f87bd77c-NRT"},{"name":"alt-svc","value":"h3=\":443\"; ma=86400"},{"name":"content-type","value":"text/html"},{"name":"age","value":"3335"},{"name":"location","value":"https://www.kalindimarketing.com/"}],"headersSize":921,"redirectURL":"https://www.kalindimarketing.com/","httpVersion":"","bodySize":0}},{"pageref":"http://kalindimarketing.com/","startedDateTime":"2026-03-06T07:58:56.753280Z","cache":{},"request":{"cookies":[],"url":"https://www.kalindimarketing.com/","queryString":[],"headers":[{"name":"accept-language","value":"en-US,en;q=0.8"},{"name":"accept-encoding","value":"gzip, deflate, br"},{"name":"accept","value":"text/html,application/xhtml+xml,application/xml;q=0.9,image/webp,image/apng,*/*;q=0.8"},{"name":"user-agent","value":"Mozilla/5.0 (X11; Linux x86_64) AppleWebKit/537.36 (KHTML, like Gecko) Ubuntu Chromium/61.0.3163.100 Chrome/61.0.3163.100 Safari/537.36 PingdomPageSpeed/1.0 (pingbot/2.0; +http://www.pingdom.com/)"},{"name":"pragma","value":"no-cache"},{"name":"cache-control","value":"no-cache"},{"name":"upgrade-insecure-requests","value":"1"}],"headersSize":467,"bodySize":0,"method":"GET","httpVersion":""},"timings":{"receive":1.0240020752,"send":0.0810027122,"ssl":0,"connect":0,"dns":0,"wait":208.0489993095,"blocked":19.8040008545},"time":228.9580049515,"response":{"status":200,"cookies":[],"statusText":"","content":{"mimeType":"text/html","_resourceType":"Document","size":31600},"headers":[{"name":"via","value":"1.1 varnish"},{"name":"cf-cache-status","value":"DYNAMIC"},{"name":"vary","value":"Accept-Encoding"},{"name":"report-to","value":"{\"group\":\"cf-nel\",\"max_age\":604800,\"endpoints\":[{\"url\":\"https://a.nel.cloudflare.com/report/v4?s=TbOZ0YAZUgMOSy9NojyRq4yZFkgO0aWLpnlc7sCyUUwS5VSS4vN7Xb4zPNBmNxMcL1xiIESyEiT3OvcBz83tyMmkoloba%2F9jGPXTCwFa26qTLJinIqXk9w%3D%3D\"}]}"},{"name":"access-control-allow-origin","value":"*"},{"name":"nel","value":"{\"report_to\":\"cf-nel\",\"success_fraction\":0.0,\"max_age\":604800}"},{"name":"x-cache-hits","value":"0"},{"name":"cache-control","value":"max-age=600"},{"name":"alt-svc","value":"h3=\":443\"; ma=86400"},{"name":"status","value":"200"},{"name":"x-served-by","value":"cache-nrt-rjtf7700095-NRT"},{"name":"x-cache","value":"MISS"},{"name":"x-github-request-id","value":"20F6:257092:4199DB:43A553:69AA8940"},{"name":"expires","value":"Fri, 06 Mar 2026 08:08:56 GMT"},{"name":"last-modified","value":"Fri, 06 Mar 2026 07:57:33 GMT"},{"name":"x-fastly-request-id","value":"1d62356cc33fa4e572bdb1351d6703e3322d357c"},{"name":"date","value":"Fri, 06 Mar 2026 07:58:56 GMT"},{"name":"cf-ray","value":"9d7fd174dd50d77c-NRT"},{"name":"x-proxy-cache","value":"MISS"},{"name":"content-encoding","value":"br"},{"name":"age","value":"0"},{"name":"x-timer","value":"S1772783937.798078,VS0,VE174"},{"name":"server","value":"cloudflare"},{"name":"server-timing","value":"cfCacheStatus;desc=\"DYNAMIC\"\ncfEdge;dur=203,cfOrigin;dur=0"},{"name":"content-type","value":"text/html; charset=utf-8"}],"headersSize":1066,"redirectURL":"","httpVersion":"","bodySize":8998}},{"pageref":"http://kalindimarketing.com/","startedDateTime":"2026-03-06T07:58:56.986449Z","cache":{},"request":{"cookies":[],"url":"https://fonts.googleapis.com/css2?family=Inter:wght@300;400;500;600;700;800;900&family=Space+Grotesk:wght@400;500;600;700&display=swap","queryString":[{"name":"family","value":"Inter:wght@300"},{"name":"family","value":"Space Grotesk:wght@400"},{"name":"display","value":"swap"}],"headers":[{"name":"accept-language","value":"en-US,en;q=0.8"},{"name":"accept-encoding","value":"gzip, deflate, br"},{"name":"accept","value":"text/css,*/*;q=0.1"},{"name":"user-agent","value":"Mozilla/5.0 (X11; Linux x86_64) AppleWebKit/537.36 (KHTML, like Gecko) Ubuntu Chromium/61.0.3163.100 Chrome/61.0.3163.100 Safari/537.36 PingdomPageSpeed/1.0 (pingbot/2.0; +http://www.pingdom.com/)"},{"name":"referer","value":"https://www.kalindimarketing.com/"},{"name":"pragma","value":"no-cache"},{"name":"cache-control","value":"no-cache"}],"headersSize":418,"bodySize":0,"method":"GET","httpVersion":""},"timings":{"receive":0.6110076904,"send":0.147998333,"ssl":14.7360116243,"connect":16.1119997501,"dns":0.6819963455,"wait":47.4319905043,"blocked":0.6770044565},"time":80.3980087042,"response":{"status":200,"cookies":[],"statusText":"","content":{"mimeType":"text/css","_resourceType":"Stylesheet","size":23501},"headers":[{"name":"status","value":"200"},{"name":"x-xss-protection","value":"0"},{"name":"x-content-type-options","value":"nosniff"},{"name":"cross-origin-resource-policy","value":"cross-origin"},{"name":"content-encoding","value":"gzip"},{"name":"strict-transport-security","value":"max-age=31536000"},{"name":"vary","value":"Sec-Fetch-Dest, Sec-Fetch-Mode, Sec-Fetch-Site"},{"name":"expires","value":"Fri, 06 Mar 2026 07:58:57 GMT"},{"name":"server","value":"ESF"},{"name":"last-modified","value":"Fri, 06 Mar 2026 07:58:57 GMT"},{"name":"link","value":"<https://fonts.gstatic.com>; rel=preconnect; crossorigin"},{"name":"cross-origin-opener-policy","value":"same-origin-allow-popups"},{"name":"cache-control","value":"private, max-age=86400, stale-while-revalidate=604800"},{"name":"date","value":"Fri, 06 Mar 2026 07:58:57 GMT"},{"name":"x-frame-options","value":"SAMEORIGIN"},{"name":"alt-svc","value":"h3=\":443\"; ma=2592000,h3-29=\":443\"; ma=2592000"},{"name":"content-type","value":"text/css; charset=utf-8"},{"name":"access-control-allow-origin","value":"*"},{"name":"timing-allow-origin","value":"*"}],"headersSize":756,"redirectURL":"","httpVersion":"","bodySize":1529}},{"pageref":"http://kalindimarketing.com/","startedDateTime":"2026-03-06T07:58:56.987558Z","cache":{},"request":{"cookies":[],"url":"https://www.kalindimarketing.com/styles/main.css","queryString":[],"headers":[{"name":"accept-language","value":"en-US,en;q=0.8"},{"name":"accept-encoding","value":"gzip, deflate, br"},{"name":"accept","value":"text/css,*/*;q=0.1"},{"name":"user-agent","value":"Mozilla/5.0 (X11; Linux x86_64) AppleWebKit/537.36 (KHTML, like Gecko) Ubuntu Chromium/61.0.3163.100 Chrome/61.0.3163.100 Safari/537.36 PingdomPageSpeed/1.0 (pingbot/2.0; +http://www.pingdom.com/)"},{"name":"referer","value":"https://www.kalindimarketing.com/"},{"name":"pragma","value":"no-cache"},{"name":"cache-control","value":"no-cache"}],"headersSize":429,"bodySize":0,"method":"GET","httpVersion":""},"timings":{"receive":0.4409942627,"send":0.236004591,"ssl":0,"connect":0,"dns":0,"wait":185.7559978962,"blocked":1.0839998722},"time":187.5169966221,"response":{"status":200,"cookies":[],"statusText":"","content":{"mimeType":"text/css","_resourceType":"Stylesheet","size":24208},"headers":[{"name":"content-length","value":"4594"},{"name":"via","value":"1.1 varnish"},{"name":"cf-cache-status","value":"MISS"},{"name":"vary","value":"Accept-Encoding"},{"name":"report-to","value":"{\"group\":\"cf-nel\",\"max_age\":604800,\"endpoints\":[{\"url\":\"https://a.nel.cloudflare.com/report/v4?s=k4TUT2W58EWOrKmSRM8abkrhkg7qGfzz6LqykVfe2VyaxYFQBi49rUgo4kMhKF8GRnU6tV0W4TGTI6TBAuW%2Fje0%2Ff4CEKXTeKZJaPdGpmM1Ce26xhZNdoA%3D%3D\"}]}"},{"name":"cf-ray","value":"9d7fd17628f5d77c-NRT"},{"name":"nel","value":"{\"report_to\":\"cf-nel\",\"success_fraction\":0.0,\"max_age\":604800}"},{"name":"etag","value":"W/\"69aa88ed-5e90\""},{"name":"x-cache-hits","value":"0"},{"name":"cache-control","value":"max-age=14400"},{"name":"alt-svc","value":"h3=\":443\"; ma=86400"},{"name":"status","value":"200"},{"name":"x-served-by","value":"cache-tyo11979-TYO"},{"name":"x-origin-cache","value":"HIT"},{"name":"x-cache","value":"MISS"},{"name":"x-github-request-id","value":"6E66:2421E3:3FE75E:41F256:69AA8940"},{"name":"accept-ranges","value":"bytes"},{"name":"expires","value":"Fri, 06 Mar 2026 08:08:57 GMT"},{"name":"last-modified","value":"Fri, 06 Mar 2026 07:57:33 GMT"},{"name":"x-fastly-request-id","value":"555685d80a99d2dcd08b73ca3bcdf3f44a90a17b"},{"name":"date","value":"Fri, 06 Mar 2026 07:58:57 GMT"},{"name":"access-control-allow-origin","value":"*"},{"name":"x-proxy-cache","value":"MISS"},{"name":"content-encoding","value":"gzip"},{"name":"age","value":"0"},{"name":"x-timer","value":"S1772783937.005607,VS0,VE164"},{"name":"server","value":"cloudflare"},{"name":"content-type","value":"text/css; charset=utf-8"}],"headersSize":1076,"redirectURL":"","httpVersion":"","bodySize":5075}},{"pageref":"http://kalindimarketing.com/","startedDateTime":"2026-03-06T07:58:56.987851Z","cache":{},"request":{"cookies":[],"url":"https://www.kalindimarketing.com/cdn-cgi/scripts/5c5dd728/cloudflare-static/email-decode.min.js","queryString":[],"headers":[{"name":"accept-language","value":"en-US,en;q=0.8"},{"name":"accept-encoding","value":"gzip, deflate, br"},{"name":"accept","value":"*/*"},{"name":"user-agent","value":"Mozilla/5.0 (X11; Linux x86_64) AppleWebKit/537.36 (KHTML, like Gecko) Ubuntu Chromium/61.0.3163.100 Chrome/61.0.3163.100 Safari/537.36 PingdomPageSpeed/1.0 (pingbot/2.0; +http://www.pingdom.com/)"},{"name":"referer","value":"https://www.kalindimarketing.com/"},{"name":"pragma","value":"no-cache"},{"name":"cache-control","value":"no-cache"}],"headersSize":461,"bodySize":0,"method":"GET","httpVersion":""},"timings":{"receive":0.3899841309,"send":0.099003315,"ssl":0,"connect":0,"dns":0,"wait":3.7039965391,"blocked":0.2280026674},"time":4.4209866524,"response":{"status":200,"cookies":[],"statusText":"","content":{"mimeType":"application/javascript","_resourceType":"Script","size":1239},"headers":[{"name":"status","value":"200"},{"name":"nel","value":"{\"report_to\":\"cf-nel\",\"success_fraction\":0.0,\"max_age\":604800}"},{"name":"x-content-type-options","value":"nosniff"},{"name":"content-encoding","value":"br"},{"name":"expires","value":"Fri, 06 Mar 2026 08:46:57 GMT"},{"name":"vary","value":"accept-encoding"},{"name":"server","value":"cloudflare"},{"name":"report-to","value":"{\"group\":\"cf-nel\",\"max_age\":604800,\"endpoints\":[{\"url\":\"https://a.nel.cloudflare.com/report/v4?s=1abQHKML5TsVtAGw6nZFaoWU%2B9LIjrQAY6f34AZ3LGaOlTcuD6MMUufpLrt%2BDO8InXuxGOSeyncbOqIIOtWbHx4UAItG%2Bn02sxiME8UDemIkhv9YcCFM8Q%3D%3D\"}]}"},{"name":"cache-control","value":"public"},{"name":"date","value":"Fri, 06 Mar 2026 07:58:57 GMT"},{"name":"x-frame-options","value":"DENY"},{"name":"content-type","value":"application/javascript"},{"name":"cf-ray","value":"9d7fd1775be8d77c-NRT"}],"headersSize":632,"redirectURL":"","httpVersion":"","bodySize":959}},{"pageref":"http://kalindimarketing.com/","startedDateTime":"2026-03-06T07:58:56.987690Z","cache":{},"request":{"cookies":[],"url":"https://www.kalindimarketing.com/styles/animations.css","queryString":[],"headers":[{"name":"accept-language","value":"en-US,en;q=0.8"},{"name":"accept-encoding","value":"gzip, deflate, br"},{"name":"accept","value":"text/css,*/*;q=0.1"},{"name":"user-agent","value":"Mozilla/5.0 (X11; Linux x86_64) AppleWebKit/537.36 (KHTML, like Gecko) Ubuntu Chromium/61.0.3163.100 Chrome/61.0.3163.100 Safari/537.36 PingdomPageSpeed/1.0 (pingbot/2.0; +http://www.pingdom.com/)"},{"name":"referer","value":"https://www.kalindimarketing.com/"},{"name":"pragma","value":"no-cache"},{"name":"cache-control","value":"no-cache"}],"headersSize":435,"bodySize":0,"method":"GET","httpVersion":""},"timings":{"receive":0.3249969482,"send":0.0769942999,"ssl":0,"connect":0,"dns":0,"wait":191.0070031881,"blocked":0.9160041809},"time":192.3249986172,"response":{"status":200,"cookies":[],"statusText":"","content":{"mimeType":"text/css","_resourceType":"Stylesheet","size":8308},"headers":[{"name":"content-length","value":"1709"},{"name":"via","value":"1.1 varnish"},{"name":"cf-cache-status","value":"MISS"},{"name":"vary","value":"Accept-Encoding"},{"name":"report-to","value":"{\"group\":\"cf-nel\",\"max_age\":604800,\"endpoints\":[{\"url\":\"https://a.nel.cloudflare.com/report/v4?s=ypZQr1rM%2ByV9%2B7VQzYsKd6%2BzSi0WgyjAqTPb0tR3qxdlzYfYuq9JCOFeNcNCjpM0TVz8aCLxrzEnbgNqDU0mMsiVxRszFZtyU9GnnFuWUs9iJjXD5eFTsA%3D%3D\"}]}"},{"name":"cf-ray","value":"9d7fd17628f7d77c-NRT"},{"name":"nel","value":"{\"report_to\":\"cf-nel\",\"success_fraction\":0.0,\"max_age\":604800}"},{"name":"etag","value":"W/\"69aa88ed-2074\""},{"name":"x-cache-hits","value":"0"},{"name":"cache-control","value":"max-age=14400"},{"name":"alt-svc","value":"h3=\":443\"; ma=86400"},{"name":"status","value":"200"},{"name":"x-served-by","value":"cache-nrt-rjtf7700063-NRT"},{"name":"x-cache","value":"MISS"},{"name":"x-github-request-id","value":"C60E:155219:412B8D:4336C8:69AA8940"},{"name":"accept-ranges","value":"bytes"},{"name":"expires","value":"Fri, 06 Mar 2026 08:08:57 GMT"},{"name":"last-modified","value":"Fri, 06 Mar 2026 07:57:33 GMT"},{"name":"x-fastly-request-id","value":"40ab20a847cd19845a2b2974ae8de7899e9ae50c"},{"name":"date","value":"Fri, 06 Mar 2026 07:58:57 GMT"},{"name":"access-control-allow-origin","value":"*"},{"name":"x-proxy-cache","value":"MISS"},{"name":"content-encoding","value":"gzip"},{"name":"age","value":"0"},{"name":"x-timer","value":"S1772783937.003385,VS0,VE171"},{"name":"server","value":"cloudflare"},{"name":"content-type","value":"text/css; charset=utf-8"}],"headersSize":1064,"redirectURL":"","httpVersion":"","bodySize":2208}},{"pageref":"http://kalindimarketing.com/","startedDateTime":"2026-03-06T07:58:57.185039Z","cache":{},"request":{"cookies":[],"url":"https://fonts.gstatic.com/s/inter/v20/UcCO3FwrK3iLTeHuS_nVMrMxCp50SjIw2boKoduKmMEVuI6fAZ9hiA.woff2","queryString":[],"headers":[{"name":"origin","value":"https://www.kalindimarketing.com"},{"name":"accept-language","value":"en-US,en;q=0.8"},{"name":"accept-encoding","value":"gzip, deflate, br"},{"name":"accept","value":"*/*"},{"name":"user-agent","value":"Mozilla/5.0 (X11; Linux x86_64) AppleWebKit/537.36 (KHTML, like Gecko) Ubuntu Chromium/61.0.3163.100 Chrome/61.0.3163.100 Safari/537.36 PingdomPageSpeed/1.0 (pingbot/2.0; +http://www.pingdom.com/)"},{"name":"referer","value":"https://fonts.googleapis.com/css2?family=Inter:wght@300;400;500;600;700;800;900&family=Space+Grotesk:wght@400;500;600;700&display=swap"},{"name":"pragma","value":"no-cache"},{"name":"cache-control","value":"no-cache"}],"headersSize":614,"bodySize":0,"method":"GET","httpVersion":""},"timings":{"receive":0.7340087891,"send":0.3660023212,"ssl":0,"connect":0,"dns":0,"wait":6.4570009708,"blocked":0.367000699},"time":7.9240127802,"response":{"status":200,"cookies":[],"statusText":"","content":{"mimeType":"font/woff2","_resourceType":"Font","size":24272},"headers":[{"name":"status","value":"200"},{"name":"content-length","value":"24272"},{"name":"x-xss-protection","value":"0"},{"name":"x-content-type-options","value":"nosniff"},{"name":"cross-origin-resource-policy","value":"cross-origin"},{"name":"age","value":"78710"},{"name":"expires","value":"Fri, 05 Mar 2027 10:07:07 GMT"},{"name":"cross-origin-opener-policy","value":"same-origin; report-to=\"apps-themes\""},{"name":"server","value":"sffe"},{"name":"content-security-policy-report-only","value":"require-trusted-types-for 'script'; report-uri https://csp.withgoogle.com/csp/apps-themes"},{"name":"last-modified","value":"Tue, 09 Sep 2025 18:36:20 GMT"},{"name":"report-to","value":"{\"group\":\"apps-themes\",\"max_age\":2592000,\"endpoints\":[{\"url\":\"https://csp.withgoogle.com/csp/report-to/apps-themes\"}]}"},{"name":"cache-control","value":"public, max-age=31536000"},{"name":"date","value":"Thu, 05 Mar 2026 10:07:07 GMT"},{"name":"access-control-allow-origin","value":"*"},{"name":"alt-svc","value":"h3=\":443\"; ma=2592000,h3-29=\":443\"; ma=2592000"},{"name":"content-type","value":"font/woff2"},{"name":"accept-ranges","value":"bytes"},{"name":"timing-allow-origin","value":"*"}],"headersSize":827,"redirectURL":"","httpVersion":"","bodySize":24813}},{"pageref":"http://kalindimarketing.com/","startedDateTime":"2026-03-06T07:58:57.185460Z","cache":{},"request":{"cookies":[],"url":"https://fonts.gstatic.com/s/inter/v20/UcCO3FwrK3iLTeHuS_nVMrMxCp50SjIw2boKoduKmMEVuGKYAZ9hiA.woff2","queryString":[],"headers":[{"name":"origin","value":"https://www.kalindimarketing.com"},{"name":"accept-language","value":"en-US,en;q=0.8"},{"name":"accept-encoding","value":"gzip, deflate, br"},{"name":"accept","value":"*/*"},{"name":"user-agent","value":"Mozilla/5.0 (X11; Linux x86_64) AppleWebKit/537.36 (KHTML, like Gecko) Ubuntu Chromium/61.0.3163.100 Chrome/61.0.3163.100 Safari/537.36 PingdomPageSpeed/1.0 (pingbot/2.0; +http://www.pingdom.com/)"},{"name":"referer","value":"https://fonts.googleapis.com/css2?family=Inter:wght@300;400;500;600;700;800;900&family=Space+Grotesk:wght@400;500;600;700&display=swap"},{"name":"pragma","value":"no-cache"},{"name":"cache-control","value":"no-cache"}],"headersSize":614,"bodySize":0,"method":"GET","httpVersion":""},"timings":{"receive":3.3279876709,"send":0.1170039177,"ssl":0,"connect":0,"dns":0,"wait":6.7940056324,"blocked":0.3859996796},"time":10.6249969006,"response":{"status":200,"cookies":[],"statusText":"","content":{"mimeType":"font/woff2","_resourceType":"Font","size":24452},"headers":[{"name":"status","value":"200"},{"name":"content-length","value":"24452"},{"name":"x-xss-protection","value":"0"},{"name":"x-content-type-options","value":"nosniff"},{"name":"cross-origin-resource-policy","value":"cross-origin"},{"name":"age","value":"162720"},{"name":"expires","value":"Thu, 04 Mar 2027 10:46:57 GMT"},{"name":"cross-origin-opener-policy","value":"same-origin; report-to=\"apps-themes\""},{"name":"server","value":"sffe"},{"name":"content-security-policy-report-only","value":"require-trusted-types-for 'script'; report-uri https://csp.withgoogle.com/csp/apps-themes"},{"name":"last-modified","value":"Tue, 09 Sep 2025 18:36:19 GMT"},{"name":"report-to","value":"{\"group\":\"apps-themes\",\"max_age\":2592000,\"endpoints\":[{\"url\":\"https://csp.withgoogle.com/csp/report-to/apps-themes\"}]}"},{"name":"cache-control","value":"public, max-age=31536000"},{"name":"date","value":"Wed, 04 Mar 2026 10:46:57 GMT"},{"name":"access-control-allow-origin","value":"*"},{"name":"alt-svc","value":"h3=\":443\"; ma=2592000,h3-29=\":443\"; ma=2592000"},{"name":"content-type","value":"font/woff2"},{"name":"accept-ranges","value":"bytes"},{"name":"timing-allow-origin","value":"*"}],"headersSize":828,"redirectURL":"","httpVersion":"","bodySize":24578}},{"pageref":"http://kalindimarketing.com/","startedDateTime":"2026-03-06T07:58:57.186402Z","cache":{},"request":{"cookies":[],"url":"https://fonts.gstatic.com/s/inter/v20/UcCO3FwrK3iLTeHuS_nVMrMxCp50SjIw2boKoduKmMEVuLyfAZ9hiA.woff2","queryString":[],"headers":[{"name":"origin","value":"https://www.kalindimarketing.com"},{"name":"accept-language","value":"en-US,en;q=0.8"},{"name":"accept-encoding","value":"gzip, deflate, br"},{"name":"accept","value":"*/*"},{"name":"user-agent","value":"Mozilla/5.0 (X11; Linux x86_64) AppleWebKit/537.36 (KHTML, like Gecko) Ubuntu Chromium/61.0.3163.100 Chrome/61.0.3163.100 Safari/537.36 PingdomPageSpeed/1.0 (pingbot/2.0; +http://www.pingdom.com/)"},{"name":"referer","value":"https://fonts.googleapis.com/css2?family=Inter:wght@300;400;500;600;700;800;900&family=Space+Grotesk:wght@400;500;600;700&display=swap"},{"name":"pragma","value":"no-cache"},{"name":"cache-control","value":"no-cache"}],"headersSize":614,"bodySize":0,"method":"GET","httpVersion":""},"timings":{"receive":0.4450073242,"send":0.0900030136,"ssl":0,"connect":0,"dns":0,"wait":9.5430016518,"blocked":0.3899931908},"time":10.4680051804,"response":{"status":200,"cookies":[],"statusText":"","content":{"mimeType":"font/woff2","_resourceType":"Font","size":23664},"headers":[{"name":"status","value":"200"},{"name":"content-length","value":"23664"},{"name":"x-xss-protection","value":"0"},{"name":"x-content-type-options","value":"nosniff"},{"name":"cross-origin-resource-policy","value":"cross-origin"},{"name":"age","value":"67813"},{"name":"expires","value":"Fri, 05 Mar 2027 13:08:44 GMT"},{"name":"cross-origin-opener-policy","value":"same-origin; report-to=\"apps-themes\""},{"name":"server","value":"sffe"},{"name":"content-security-policy-report-only","value":"require-trusted-types-for 'script'; report-uri https://csp.withgoogle.com/csp/apps-themes"},{"name":"last-modified","value":"Tue, 09 Sep 2025 18:36:19 GMT"},{"name":"report-to","value":"{\"group\":\"apps-themes\",\"max_age\":2592000,\"endpoints\":[{\"url\":\"https://csp.withgoogle.com/csp/report-to/apps-themes\"}]}"},{"name":"cache-control","value":"public, max-age=31536000"},{"name":"date","value":"Thu, 05 Mar 2026 13:08:44 GMT"},{"name":"access-control-allow-origin","value":"*"},{"name":"alt-svc","value":"h3=\":443\"; ma=2592000,h3-29=\":443\"; ma=2592000"},{"name":"content-type","value":"font/woff2"},{"name":"accept-ranges","value":"bytes"},{"name":"timing-allow-origin","value":"*"}],"headersSize":827,"redirectURL":"","httpVersion":"","bodySize":23767}},{"pageref":"http://kalindimarketing.com/","startedDateTime":"2026-03-06T07:58:57.186208Z","cache":{},"request":{"cookies":[],"url":"https://fonts.gstatic.com/s/spacegrotesk/v22/V8mQoQDjQSkFtoMM3T6r8E7mF71Q-gOoraIAEj4PVnskPMA.woff2","queryString":[],"headers":[{"name":"origin","value":"https://www.kalindimarketing.com"},{"name":"accept-language","value":"en-US,en;q=0.8"},{"name":"accept-encoding","value":"gzip, deflate, br"},{"name":"accept","value":"*/*"},{"name":"user-agent","value":"Mozilla/5.0 (X11; Linux x86_64) AppleWebKit/537.36 (KHTML, like Gecko) Ubuntu Chromium/61.0.3163.100 Chrome/61.0.3163.100 Safari/537.36 PingdomPageSpeed/1.0 (pingbot/2.0; +http://www.pingdom.com/)"},{"name":"referer","value":"https://fonts.googleapis.com/css2?family=Inter:wght@300;400;500;600;700;800;900&family=Space+Grotesk:wght@400;500;600;700&display=swap"},{"name":"pragma","value":"no-cache"},{"name":"cache-control","value":"no-cache"}],"headersSize":614,"bodySize":0,"method":"GET","httpVersion":""},"timings":{"receive":0.2889862061,"send":0.2010017633,"ssl":0,"connect":0,"dns":0,"wait":10.2609992027,"blocked":0.4539936781},"time":11.2049808502,"response":{"status":200,"cookies":[],"statusText":"","content":{"mimeType":"font/woff2","_resourceType":"Font","size":12840},"headers":[{"name":"status","value":"200"},{"name":"content-length","value":"12840"},{"name":"x-xss-protection","value":"0"},{"name":"x-content-type-options","value":"nosniff"},{"name":"cross-origin-resource-policy","value":"cross-origin"},{"name":"age","value":"61060"},{"name":"expires","value":"Fri, 05 Mar 2027 15:01:17 GMT"},{"name":"cross-origin-opener-policy","value":"same-origin; report-to=\"apps-themes\""},{"name":"server","value":"sffe"},{"name":"content-security-policy-report-only","value":"require-trusted-types-for 'script'; report-uri https://csp.withgoogle.com/csp/apps-themes"},{"name":"last-modified","value":"Thu, 04 Sep 2025 17:26:38 GMT"},{"name":"report-to","value":"{\"group\":\"apps-themes\",\"max_age\":2592000,\"endpoints\":[{\"url\":\"https://csp.withgoogle.com/csp/report-to/apps-themes\"}]}"},{"name":"cache-control","value":"public, max-age=31536000"},{"name":"date","value":"Thu, 05 Mar 2026 15:01:17 GMT"},{"name":"access-control-allow-origin","value":"*"},{"name":"alt-svc","value":"h3=\":443\"; ma=2592000,h3-29=\":443\"; ma=2592000"},{"name":"content-type","value":"font/woff2"},{"name":"accept-ranges","value":"bytes"},{"name":"timing-allow-origin","value":"*"}],"headersSize":827,"redirectURL":"","httpVersion":"","bodySize":12957}},{"pageref":"http://kalindimarketing.com/","startedDateTime":"2026-03-06T07:58:57.188293Z","cache":{},"request":{"cookies":[],"url":"https://fonts.gstatic.com/s/inter/v20/UcCO3FwrK3iLTeHuS_nVMrMxCp50SjIw2boKoduKmMEVuFuYAZ9hiA.woff2","queryString":[],"headers":[{"name":"origin","value":"https://www.kalindimarketing.com"},{"name":"accept-language","value":"en-US,en;q=0.8"},{"name":"accept-encoding","value":"gzip, deflate, br"},{"name":"accept","value":"*/*"},{"name":"user-agent","value":"Mozilla/5.0 (X11; Linux x86_64) AppleWebKit/537.36 (KHTML, like Gecko) Ubuntu Chromium/61.0.3163.100 Chrome/61.0.3163.100 Safari/537.36 PingdomPageSpeed/1.0 (pingbot/2.0; +http://www.pingdom.com/)"},{"name":"referer","value":"https://fonts.googleapis.com/css2?family=Inter:wght@300;400;500;600;700;800;900&family=Space+Grotesk:wght@400;500;600;700&display=swap"},{"name":"pragma","value":"no-cache"},{"name":"cache-control","value":"no-cache"}],"headersSize":614,"bodySize":0,"method":"GET","httpVersion":""},"timings":{"receive":0.3660125732,"send":0.0989884138,"ssl":0,"connect":0,"dns":0,"wait":12.8870010376,"blocked":0.2180039883},"time":13.5700060129,"response":{"status":200,"cookies":[],"statusText":"","content":{"mimeType":"font/woff2","_resourceType":"Font","size":24356},"headers":[{"name":"status","value":"200"},{"name":"content-length","value":"24356"},{"name":"x-xss-protection","value":"0"},{"name":"x-content-type-options","value":"nosniff"},{"name":"cross-origin-resource-policy","value":"cross-origin"},{"name":"age","value":"65530"},{"name":"expires","value":"Fri, 05 Mar 2027 13:46:47 GMT"},{"name":"cross-origin-opener-policy","value":"same-origin; report-to=\"apps-themes\""},{"name":"server","value":"sffe"},{"name":"content-security-policy-report-only","value":"require-trusted-types-for 'script'; report-uri https://csp.withgoogle.com/csp/apps-themes"},{"name":"last-modified","value":"Tue, 09 Sep 2025 18:36:20 GMT"},{"name":"report-to","value":"{\"group\":\"apps-themes\",\"max_age\":2592000,\"endpoints\":[{\"url\":\"https://csp.withgoogle.com/csp/report-to/apps-themes\"}]}"},{"name":"cache-control","value":"public, max-age=31536000"},{"name":"date","value":"Thu, 05 Mar 2026 13:46:47 GMT"},{"name":"access-control-allow-origin","value":"*"},{"name":"alt-svc","value":"h3=\":443\"; ma=2592000,h3-29=\":443\"; ma=2592000"},{"name":"content-type","value":"font/woff2"},{"name":"accept-ranges","value":"bytes"},{"name":"timing-allow-origin","value":"*"}],"headersSize":827,"redirectURL":"","httpVersion":"","bodySize":24460}},{"pageref":"http://kalindimarketing.com/","startedDateTime":"2026-03-06T07:58:56.988020Z","cache":{},"request":{"cookies":[],"url":"https://static.cloudflareinsights.com/beacon.min.js/v8c78df7c7c0f484497ecbca7046644da1771523124516","queryString":[],"headers":[{"name":"origin","value":"https://www.kalindimarketing.com"},{"name":"accept-language","value":"en-US,en;q=0.8"},{"name":"accept-encoding","value":"gzip, deflate, br"},{"name":"accept","value":"*/*"},{"name":"user-agent","value":"Mozilla/5.0 (X11; Linux x86_64) AppleWebKit/537.36 (KHTML, like Gecko) Ubuntu Chromium/61.0.3163.100 Chrome/61.0.3163.100 Safari/537.36 PingdomPageSpeed/1.0 (pingbot/2.0; +http://www.pingdom.com/)"},{"name":"referer","value":"https://www.kalindimarketing.com/"},{"name":"pragma","value":"no-cache"},{"name":"cache-control","value":"no-cache"}],"headersSize":501,"bodySize":0,"method":"GET","httpVersion":""},"timings":{"receive":0.8040008545,"send":0.1119971275,"ssl":17.0789957047,"connect":19.8120027781,"dns":0.3580003977,"wait":12.1019929647,"blocked":0.2689957619},"time":50.535985589,"response":{"status":200,"cookies":[],"statusText":"","content":{"mimeType":"text/javascript","_resourceType":"Script","size":31169},"headers":[{"name":"status","value":"200"},{"name":"cross-origin-resource-policy","value":"cross-origin"},{"name":"content-encoding","value":"gzip"},{"name":"vary","value":"Accept-Encoding"},{"name":"server","value":"cloudflare"},{"name":"last-modified","value":"Thu, 19 Feb 2026 17:45:24 GMT"},{"name":"etag","value":"W/\"2026.2.0\""},{"name":"cache-control","value":"public, max-age=86400"},{"name":"date","value":"Fri, 06 Mar 2026 07:58:57 GMT"},{"name":"access-control-allow-origin","value":"*"},{"name":"content-type","value":"text/javascript;charset=UTF-8"},{"name":"cf-ray","value":"9d7fd1778f69acf2-NRT"}],"headersSize":389,"redirectURL":"","httpVersion":"","bodySize":11089}},{"pageref":"http://kalindimarketing.com/","startedDateTime":"2026-03-06T07:58:56.987934Z","cache":{},"request":{"cookies":[],"url":"https://www.kalindimarketing.com/scripts/main.js","queryString":[],"headers":[{"name":"accept-language","value":"en-US,en;q=0.8"},{"name":"accept-encoding","value":"gzip, deflate, br"},{"name":"accept","value":"*/*"},{"name":"user-agent","value":"Mozilla/5.0 (X11; Linux x86_64) AppleWebKit/537.36 (KHTML, like Gecko) Ubuntu Chromium/61.0.3163.100 Chrome/61.0.3163.100 Safari/537.36 PingdomPageSpeed/1.0 (pingbot/2.0; +http://www.pingdom.com/)"},{"name":"referer","value":"https://www.kalindimarketing.com/"},{"name":"pragma","value":"no-cache"},{"name":"cache-control","value":"no-cache"}],"headersSize":414,"bodySize":0,"method":"GET","httpVersion":""},"timings":{"receive":0.4679870605,"send":0.2049952745,"ssl":0,"connect":0,"dns":0,"wait":185.7469975948,"blocked":0.269010663},"time":186.688990593,"response":{"status":200,"cookies":[],"statusText":"","content":{"mimeType":"application/javascript","_resourceType":"Script","size":7992},"headers":[{"name":"content-length","value":"2573"},{"name":"via","value":"1.1 varnish"},{"name":"cf-cache-status","value":"MISS"},{"name":"vary","value":"Accept-Encoding"},{"name":"report-to","value":"{\"group\":\"cf-nel\",\"max_age\":604800,\"endpoints\":[{\"url\":\"https://a.nel.cloudflare.com/report/v4?s=qM1boszFNyIRNO98%2B7vXxNmrBm1N8K6o3X7fcSOciVPX4E4UgDMwzf6I98XGoSPXIC%2FzCigjg6qchSPg0Ynrpd%2FzrF7h8iRio8DNq9z8vBxDmLMcQnNzvw%3D%3D\"}]}"},{"name":"cf-ray","value":"9d7fd1776c06d77c-NRT"},{"name":"nel","value":"{\"report_to\":\"cf-nel\",\"success_fraction\":0.0,\"max_age\":604800}"},{"name":"etag","value":"W/\"69aa88ed-1f38\""},{"name":"x-cache-hits","value":"0"},{"name":"cache-control","value":"max-age=14400"},{"name":"alt-svc","value":"h3=\":443\"; ma=86400"},{"name":"status","value":"200"},{"name":"x-served-by","value":"cache-tyo11945-TYO"},{"name":"x-origin-cache","value":"HIT"},{"name":"x-cache","value":"MISS"},{"name":"x-github-request-id","value":"91F2:2E38C:405329:425E85:69AA8941"},{"name":"accept-ranges","value":"bytes"},{"name":"expires","value":"Fri, 06 Mar 2026 08:08:57 GMT"},{"name":"last-modified","value":"Fri, 06 Mar 2026 07:57:33 GMT"},{"name":"x-fastly-request-id","value":"e10e3b372bc3fee1c896706ced7b9e70b384bcd0"},{"name":"date","value":"Fri, 06 Mar 2026 07:58:57 GMT"},{"name":"access-control-allow-origin","value":"*"},{"name":"x-proxy-cache","value":"MISS"},{"name":"content-encoding","value":"gzip"},{"name":"age","value":"0"},{"name":"x-timer","value":"S1772783937.199085,VS0,VE166"},{"name":"server","value":"cloudflare"},{"name":"content-type","value":"application/javascript; charset=utf-8"}],"headersSize":1091,"redirectURL":"","httpVersion":"","bodySize":2997}},{"pageref":"http://kalindimarketing.com/","startedDateTime":"2026-03-06T07:58:56.987761Z","cache":{},"request":{"cookies":[],"url":"https://www.kalindimarketing.com/assets/logo.webp","queryString":[],"headers":[{"name":"accept-language","value":"en-US,en;q=0.8"},{"name":"accept-encoding","value":"gzip, deflate, br"},{"name":"accept","value":"image/webp,image/apng,image/*,*/*;q=0.8"},{"name":"user-agent","value":"Mozilla/5.0 (X11; Linux x86_64) AppleWebKit/537.36 (KHTML, like Gecko) Ubuntu Chromium/61.0.3163.100 Chrome/61.0.3163.100 Safari/537.36 PingdomPageSpeed/1.0 (pingbot/2.0; +http://www.pingdom.com/)"},{"name":"referer","value":"https://www.kalindimarketing.com/"},{"name":"pragma","value":"no-cache"},{"name":"cache-control","value":"no-cache"}],"headersSize":451,"bodySize":0,"method":"GET","httpVersion":""},"timings":{"receive":1.3740081787,"send":0.092998147,"ssl":0,"connect":0,"dns":0,"wait":201.200991869,"blocked":0.2669990063},"time":202.934997201,"response":{"status":200,"cookies":[],"statusText":"","content":{"mimeType":"image/webp","_resourceType":"Image","size":97654},"headers":[{"name":"content-length","value":"97654"},{"name":"via","value":"1.1 varnish"},{"name":"cf-cache-status","value":"MISS"},{"name":"vary","value":"Accept-Encoding"},{"name":"report-to","value":"{\"group\":\"cf-nel\",\"max_age\":604800,\"endpoints\":[{\"url\":\"https://a.nel.cloudflare.com/report/v4?s=7DWiKy5oUHBiccfhYDz1nnZxdHyVm%2FYfojyOhbUrewZx2LTO60qV421g65IFprPpeAiu%2BoS5uvcz79BhIJZSDtjmg0mzDdOy9BBMLLOc1JWNwKdbuT5qPg%3D%3D\"}]}"},{"name":"cf-ray","value":"9d7fd1776bffd77c-NRT"},{"name":"nel","value":"{\"report_to\":\"cf-nel\",\"success_fraction\":0.0,\"max_age\":604800}"},{"name":"etag","value":"\"69aa88ed-17d76\""},{"name":"x-cache-hits","value":"0"},{"name":"cache-control","value":"max-age=14400"},{"name":"alt-svc","value":"h3=\":443\"; ma=86400"},{"name":"status","value":"200"},{"name":"x-served-by","value":"cache-tyo11960-TYO"},{"name":"x-cache","value":"MISS"},{"name":"x-github-request-id","value":"5DBC:3B9CC1:4104D9:431012:69AA8940"},{"name":"accept-ranges","value":"bytes"},{"name":"expires","value":"Fri, 06 Mar 2026 08:08:57 GMT"},{"name":"last-modified","value":"Fri, 06 Mar 2026 07:57:33 GMT"},{"name":"x-fastly-request-id","value":"909a25d442fb67aa0da8c93bf5ea4c140ec7705d"},{"name":"date","value":"Fri, 06 Mar 2026 07:58:57 GMT"},{"name":"access-control-allow-origin","value":"*"},{"name":"x-proxy-cache","value":"MISS"},{"name":"age","value":"0"},{"name":"x-timer","value":"S1772783937.197531,VS0,VE181"},{"name":"server","value":"cloudflare"},{"name":"content-type","value":"image/webp"}],"headersSize":1018,"redirectURL":"","httpVersion":"","bodySize":98190}},{"pageref":"http://kalindimarketing.com/","startedDateTime":"2026-03-06T07:58:57.500273Z","cache":{},"request":{"cookies":[],"url":"https://www.kalindimarketing.com/assets/logo.webp","queryString":[],"headers":[{"name":"accept-language","value":"en-US,en;q=0.8"},{"name":"accept-encoding","value":"gzip, deflate, br"},{"name":"accept","value":"image/webp,image/apng,image/*,*/*;q=0.8"},{"name":"user-agent","value":"Mozilla/5.0 (X11; Linux x86_64) AppleWebKit/537.36 (KHTML, like Gecko) Ubuntu Chromium/61.0.3163.100 Chrome/61.0.3163.100 Safari/537.36 PingdomPageSpeed/1.0 (pingbot/2.0; +http://www.pingdom.com/)"},{"name":"referer","value":"https://www.kalindimarketing.com/"},{"name":"pragma","value":"no-cache"},{"name":"cache-control","value":"no-cache"}],"headersSize":451,"bodySize":0,"method":"GET","httpVersion":""},"timings":{"receive":1.0350036621,"send":0.2159923315,"ssl":0,"connect":0,"dns":0,"wait":6.8050026894,"blocked":0.3440082073},"time":8.4000068903,"response":{"status":200,"cookies":[],"statusText":"","content":{"mimeType":"image/webp","_resourceType":"Other","size":97654},"headers":[{"name":"content-length","value":"97654"},{"name":"via","value":"1.1 varnish"},{"name":"cf-cache-status","value":"HIT"},{"name":"vary","value":"Accept-Encoding"},{"name":"report-to","value":"{\"group\":\"cf-nel\",\"max_age\":604800,\"endpoints\":[{\"url\":\"https://a.nel.cloudflare.com/report/v4?s=EtDfqOfF3E0l3MyjlRAWDI6HaW1Ew9ngDR01t%2BrOkRA5%2FKl0q77SIscJiHa%2FQshpkq0J8SLL1rXJwBsqD4fKYeCVeEzJs9Wa3ks4DyADWmjSqdtfGmifZw%3D%3D\"}]}"},{"name":"cf-ray","value":"9d7fd17968f7d77c-NRT"},{"name":"nel","value":"{\"report_to\":\"cf-nel\",\"success_fraction\":0.0,\"max_age\":604800}"},{"name":"etag","value":"\"69aa88ed-17d76\""},{"name":"x-cache-hits","value":"0"},{"name":"cache-control","value":"max-age=14400"},{"name":"alt-svc","value":"h3=\":443\"; ma=86400"},{"name":"status","value":"200"},{"name":"x-served-by","value":"cache-tyo11960-TYO"},{"name":"x-cache","value":"MISS"},{"name":"x-github-request-id","value":"5DBC:3B9CC1:4104D9:431012:69AA8940"},{"name":"accept-ranges","value":"bytes"},{"name":"expires","value":"Fri, 06 Mar 2026 08:08:57 GMT"},{"name":"last-modified","value":"Fri, 06 Mar 2026 07:57:33 GMT"},{"name":"x-fastly-request-id","value":"909a25d442fb67aa0da8c93bf5ea4c140ec7705d"},{"name":"date","value":"Fri, 06 Mar 2026 07:58:57 GMT"},{"name":"access-control-allow-origin","value":"*"},{"name":"x-proxy-cache","value":"MISS"},{"name":"age","value":"0"},{"name":"x-timer","value":"S1772783937.197531,VS0,VE181"},{"name":"server","value":"cloudflare"},{"name":"content-type","value":"image/webp"}],"headersSize":1019,"redirectURL":"","httpVersion":"","bodySize":98088}},{"pageref":"http://kalindimarketing.com/","startedDateTime":"2026-03-06T07:58:57.393577Z","cache":{},"request":{"cookies":[],"url":"https://www.kalindimarketing.com/cdn-cgi/rum?","queryString":[],"headers":[{"name":"origin","value":"https://www.kalindimarketing.com"},{"name":"content-length","value":"852"},{"name":"accept-language","value":"en-US,en;q=0.8"},{"name":"accept-encoding","value":"gzip, deflate, br"},{"name":"accept","value":"*/*"},{"name":"user-agent","value":"Mozilla/5.0 (X11; Linux x86_64) AppleWebKit/537.36 (KHTML, like Gecko) Ubuntu Chromium/61.0.3163.100 Chrome/61.0.3163.100 Safari/537.36 PingdomPageSpeed/1.0 (pingbot/2.0; +http://www.pingdom.com/)"},{"name":"referer","value":"https://www.kalindimarketing.com/"},{"name":"pragma","value":"no-cache"},{"name":"cache-control","value":"no-cache"},{"name":"content-type","value":"application/json"}],"headersSize":505,"bodySize":852,"method":"POST","httpVersion":""},"timings":{"receive":0.3540039062,"send":0.1659989357,"ssl":0,"connect":0,"dns":0,"wait":244.3279922009,"blocked":0.1730024815},"time":245.0209975243,"response":{"status":204,"cookies":[],"statusText":"","content":{"mimeType":"text/plain","_resourceType":"XHR","size":0},"headers":[{"name":"status","value":"204"},{"name":"nel","value":"{\"report_to\":\"cf-nel\",\"success_fraction\":0.0,\"max_age\":604800}"},{"name":"access-control-allow-methods","value":"POST,OPTIONS"},{"name":"access-control-max-age","value":"86400"},{"name":"vary","value":"Origin"},{"name":"server","value":"cloudflare"},{"name":"report-to","value":"{\"group\":\"cf-nel\",\"max_age\":604800,\"endpoints\":[{\"url\":\"https://a.nel.cloudflare.com/report/v4?s=JK5dFEq%2F29dcbo%2Bo%2BkyiHhIPpIGZXLHTd%2Fnw3hmfExaVXy90fin5pZjchxVj%2Fz2svAkbwY0TVJrqv5z7RLh3MJb%2FSSzEqsCC19%2BznQ4n9nTJaJdB8RDDWQ%3D%3D\"}]}"},{"name":"access-control-allow-credentials","value":"true"},{"name":"date","value":"Fri, 06 Mar 2026 07:58:57 GMT"},{"name":"access-control-allow-origin","value":"https://www.kalindimarketing.com"},{"name":"alt-svc","value":"h3=\":443\"; ma=86400"},{"name":"content-type","value":"text/plain"},{"name":"cf-ray","value":"9d7fd178bf64d77c-NRT"}],"headersSize":686,"redirectURL":"","httpVersion":"","bodySize":367}}]}}